budget/__init__.py
budget/admin.py
budget/apps.py
budget/filters.py
budget/models.py
budget/paginators.py
budget/querysets.py
budget/serializers.py
budget/signals.py
budget/urls.py
budget/utils.py
budget/validators.py
budget/views.py
budget/management/__init__.py
budget/management/commands/__init__.py
budget/management/commands/budget_reminder.py
budget/management/commands/delete_orphans.py
budget/migrations/0001_initial.py
budget/migrations/0002_auto_20160328_1347.py
budget/migrations/0003_auto_20160420_1800.py
budget/migrations/0004_auto_20160424_1343.py
budget/migrations/0005_auto_20160531_1058.py
budget/migrations/0006_auto_20160531_1717.py
budget/migrations/0007_auto_20160531_1748.py
budget/migrations/0008_package_publish_date.py
budget/migrations/0009_auto_20160623_1521.py
budget/migrations/0009_auto_20160623_2139.py
budget/migrations/0010_package_print_run_date.py
budget/migrations/0011_alter_print_run_date.py
budget/migrations/0012_merge.py
budget/migrations/0013_auto_20160627_1006.py
budget/migrations/0014_remove_item_subscribers.py
budget/migrations/0015_auto_20160627_1308.py
budget/migrations/0016_auto_20160627_1312.py
budget/migrations/0017_auto_20160627_1750.py
budget/migrations/0018_auto_20160628_1037.py
budget/migrations/0019_auto_20160628_1251.py
budget/migrations/0020_remove_package_serialized_object.py
budget/migrations/0021_auto_20160630_1736.py
budget/migrations/0022_package_print_system_slug.py
budget/migrations/0023_auto_20160819_1310.py
budget/migrations/0024_auto_20160824_0945.py
budget/migrations/0025_auto_20170817_1931.py
budget/migrations/0026_auto_20170818_1123.py
budget/migrations/0027_auto_20170820_1820.py
budget/migrations/0028_auto_20170820_1830.py
budget/migrations/0029_alter_slugs.py
budget/migrations/0030_auto_20170820_2132.py
budget/migrations/0031_auto_20170821_1251.py
budget/migrations/0032_auto_20170924_1204.py
budget/migrations/0033_contentplacement.py
budget/migrations/0034_contentplacement_populate.py
django_budget-0.9.10.dist-info/LICENSE
django_budget-0.9.10.dist-info/METADATA
django_budget-0.9.10.dist-info/WHEEL
django_budget-0.9.10.dist-info/top_level.txt
django_budget-0.9.10.dist-info/RECORD
