Metadata-Version: 2.1
Name: django-budget
Version: 0.9.10
Summary: A tool to help newsrooms manage their content, from pitch to planning to production.
Home-page: https://github.com/DallasMorningNews/django-budget/
Author: Allan James Vestal, The Dallas Morning News
Author-email: newsapps@dallasnews.com
License: AGPLv3
Download-URL: https://github.com/DallasMorningNews/django-budget/archive/0.9.10.tar.gz
Platform: UNKNOWN
Classifier: Environment :: Web Environment
Classifier: Framework :: Django
Classifier: Intended Audience :: Developers
Classifier: License :: OSI Approved :: GNU Affero General Public License v3
Classifier: Operating System :: OS Independent
Classifier: Programming Language :: Python
Classifier: Programming Language :: Python :: 2
Classifier: Programming Language :: Python :: 2.6
Classifier: Programming Language :: Python :: 2.7
Classifier: Programming Language :: Python :: 3
Classifier: Programming Language :: Python :: 3.4
Classifier: Programming Language :: Python :: 3.5
Classifier: Topic :: Internet :: WWW/HTTP
Classifier: Topic :: Internet :: WWW/HTTP :: Dynamic Content
Requires-Dist: Django (>=1.11.0)
Requires-Dist: django-admin-sortable2 (~=0.6.16)
Requires-Dist: django-editorial-staff (>=0.7.1)
Requires-Dist: django-filter (~=1.0.0)
Requires-Dist: djangorestframework (~=3.6.0)
Requires-Dist: djangorestframework-camel-case (~=0.2.0)
Requires-Dist: python-dateutil (~=2.6.1)
Requires-Dist: pytz
Requires-Dist: redis (>=2.10.6)
Requires-Dist: requests (>=2.18.4)
Requires-Dist: six (>=1.11.0)
